README.md
setup.cfg
setup.py
design_bench/__init__.py
design_bench/disk_resource.py
design_bench/registration.py
design_bench/task.py
design_bench.egg-info/PKG-INFO
design_bench.egg-info/SOURCES.txt
design_bench.egg-info/dependency_links.txt
design_bench.egg-info/requires.txt
design_bench.egg-info/top_level.txt
design_bench/datasets/__init__.py
design_bench/datasets/continuous_dataset.py
design_bench/datasets/dataset_builder.py
design_bench/datasets/discrete_dataset.py
design_bench/datasets/continuous/__init__.py
design_bench/datasets/continuous/ant_morphology_dataset.py
design_bench/datasets/continuous/dkitty_morphology_dataset.py
design_bench/datasets/continuous/hopper_controller_dataset.py
design_bench/datasets/continuous/superconductor_dataset.py
design_bench/datasets/continuous/toy_continuous_dataset.py
design_bench/datasets/discrete/__init__.py
design_bench/datasets/discrete/chembl_dataset.py
design_bench/datasets/discrete/cifar_nas_dataset.py
design_bench/datasets/discrete/gfp_dataset.py
design_bench/datasets/discrete/nas_bench_dataset.py
design_bench/datasets/discrete/tf_bind_10_dataset.py
design_bench/datasets/discrete/tf_bind_8_dataset.py
design_bench/datasets/discrete/toy_discrete_dataset.py
design_bench/datasets/discrete/utr_dataset.py
design_bench/oracles/__init__.py
design_bench/oracles/approximate_oracle.py
design_bench/oracles/exact_oracle.py
design_bench/oracles/oracle_builder.py
design_bench/oracles/exact/__init__.py
design_bench/oracles/exact/ant_morphology_oracle.py
design_bench/oracles/exact/cifar_nas_oracle.py
design_bench/oracles/exact/dkitty_morphology_oracle.py
design_bench/oracles/exact/hopper_controller_oracle.py
design_bench/oracles/exact/nas_bench_oracle.py
design_bench/oracles/exact/tf_bind_10_oracle.py
design_bench/oracles/exact/tf_bind_8_oracle.py
design_bench/oracles/exact/toy_continuous_oracle.py
design_bench/oracles/exact/toy_discrete_oracle.py
design_bench/oracles/feature_extractors/__init__.py
design_bench/oracles/feature_extractors/feature_extractor.py
design_bench/oracles/feature_extractors/morgan_fingerprint_features.py
design_bench/oracles/sklearn/__init__.py
