Metadata-Version: 2.1
Name: design-bench
Version: 2.0.16
Summary: Design-Bench: Benchmarks for Data-Driven Offline Model-Based Optimization
Home-page: https://github.com/brandontrabucco/design-bench
Author: Brandon Trabucco
Author-email: brandon@btrabucco.com
License: MIT
Download-URL: https://github.com/brandontrabucco/design-bench/archive/v2_0_16.tar.gz
Keywords: Deep Learning,Neural Networks,Benchmark,Model-Based Optimization
Platform: UNKNOWN
Classifier: Intended Audience :: Developers
Classifier: Intended Audience :: Science/Research
Classifier: Topic :: Scientific/Engineering
Classifier: Topic :: Scientific/Engineering :: Artificial Intelligence
Classifier: Topic :: Scientific/Engineering :: Mathematics
Classifier: Topic :: Software Development
Classifier: Topic :: Software Development :: Libraries
Classifier: Topic :: Software Development :: Libraries :: Python Modules
Classifier: License :: OSI Approved :: MIT License
Classifier: Programming Language :: Python :: 3
Classifier: Programming Language :: Python :: 3.7
Classifier: Programming Language :: Python :: 3.8
Provides-Extra: all
Provides-Extra: cma
